databricks_common/__init__.py
databricks_common/common.py
databricks_common/main.py
databricks_common/utils/get_spark.py
databricks_common/utils/get_spark_local.py
databricks_common/utils/logger_utils.py
databricks_common-0.1.8.dist-info/METADATA
databricks_common-0.1.8.dist-info/WHEEL
databricks_common-0.1.8.dist-info/RECORD
