Metadata-Version: 2.1
Name: databricks-common
Version: 0.1.8
Summary: 
Author: Xavier Armitage
Author-email: xtarmitage@gmail.com
Requires-Python: >=3.10,<4.0
Classifier: Programming Language :: Python :: 3
Classifier: Programming Language :: Python :: 3.10
Classifier: Programming Language :: Python :: 3.11
Requires-Dist: databricks-connect (>=13.0.0,<13.1.0)
